test_evaluator/__init__.py
test_evaluator/evaluator.py
test_evaluator-0.1.0.dist-info/licenses/LICENSE
test_evaluator-0.1.0.dist-info/METADATA
test_evaluator-0.1.0.dist-info/WHEEL
test_evaluator-0.1.0.dist-info/top_level.txt
test_evaluator-0.1.0.dist-info/RECORD
