Metadata-Version: 2.4
Name: test-evaluator
Version: 0.1.0
Summary: Simple library to evaluate test cases using input-output dictionaries
Home-page: https://github.com/yourusername/test-evaluator
Author: Your Name
Author-email: your.email@example.com
Classifier: Programming Language :: Python :: 3
Classifier: License :: OSI Approved :: MIT License
Classifier: Operating System :: OS Independent
Requires-Python: >=3.6
License-File: LICENSE
Dynamic: author
Dynamic: author-email
Dynamic: classifier
Dynamic: description-content-type
Dynamic: home-page
Dynamic: license-file
Dynamic: requires-python
Dynamic: summary
